wisetimer/__init__.py
wisetimer/analyze.py
wisetimer/benchmark.py
wisetimer/timer.py
wisetimer-1.2.0.dist-info/licenses/LICENSE.txt
wisetimer-1.2.0.dist-info/METADATA
wisetimer-1.2.0.dist-info/WHEEL
wisetimer-1.2.0.dist-info/top_level.txt
wisetimer-1.2.0.dist-info/RECORD
