Metadata-Version: 2.4
Name: wisetimer
Version: 1.2.0
Summary: Smart timer with limits, code comparison and analysis
Home-page: https://github.com/AndreyProgramMaker/wisetimer
Author: Andrey Egupov (11-year-old-developer)
Author-email: and302014@gmail.com
License: MIT
Keywords: timer,benchmark,performance
Classifier: Programming Language :: Python :: 3
Classifier: License :: OSI Approved :: MIT License
Classifier: Operating System :: OS Independent
Requires-Python: >=3.6
License-File: LICENSE.txt
Requires-Dist: keyring>=23.0
Requires-Dist: google-genai>=1.0.0
Dynamic: author
Dynamic: author-email
Dynamic: classifier
Dynamic: description
Dynamic: description-content-type
Dynamic: home-page
Dynamic: keywords
Dynamic: license
Dynamic: license-file
Dynamic: requires-dist
Dynamic: requires-python
Dynamic: summary
